generallibrary/__init__.py
generallibrary/analyze.py
generallibrary/code.py
generallibrary/context.py
generallibrary/decorators.py
generallibrary/diagram.py
generallibrary/functions.py
generallibrary/iterables.py
generallibrary/object.py
generallibrary/serialize.py
generallibrary/text.py
generallibrary/time.py
generallibrary/types.py
generallibrary/values.py
generallibrary/versions.py
generallibrary/objinfo/children.py
generallibrary/objinfo/objinfo.py
generallibrary/objinfo/origin.py
generallibrary/objinfo/parents.py
generallibrary/objinfo/properties.py
generallibrary/objinfo/type.py
generallibrary/test/calltable_objinfo.py
generallibrary/test/calltable_origin.py
generallibrary/test/positional.py
generallibrary/test/test_code.py
generallibrary/test/test_context.py
generallibrary/test/test_dataclass.py
generallibrary/test/test_decorators.py
generallibrary/test/test_diagram.py
generallibrary/test/test_functions.py
generallibrary/test/test_generallibrary.py
generallibrary/test/test_iterables.py
generallibrary/test/test_object.py
generallibrary/test/test_serialize.py
generallibrary/test/test_text.py
generallibrary/test/test_time.py
generallibrary/test/test_types.py
generallibrary/test/test_values.py
generallibrary/test/test_versions.py
generallibrary-2.10.0.dist-info/LICENSE
generallibrary-2.10.0.dist-info/METADATA
generallibrary-2.10.0.dist-info/WHEEL
generallibrary-2.10.0.dist-info/top_level.txt
generallibrary-2.10.0.dist-info/RECORD
