Metadata-Version: 2.1
Name: generallibrary
Version: 2.10.0
Summary: Random useful code categorized into modules.
Home-page: https://github.com/ManderaGeneral/generallibrary
Author: Rickard "Mandera" Abraham
Author-email: rickard.abraham@gmail.com
License: apache2
Classifier: Topic :: Software Development :: Libraries
Classifier: Programming Language :: Python :: 3.8
Classifier: Programming Language :: Python :: 3.9
Classifier: Programming Language :: Python :: 3.10
Classifier: Programming Language :: Python :: 3.11
Classifier: Programming Language :: Python :: 3.12
Classifier: License :: OSI Approved :: Apache Software License
Classifier: Operating System :: Microsoft :: Windows
Classifier: Operating System :: POSIX :: Linux
License-File: LICENSE
Requires-Dist: generalimport
Requires-Dist: generaltool
Requires-Dist: packaging
Requires-Dist: pyperclip
Requires-Dist: pytz
Requires-Dist: dill
Provides-Extra: full
Requires-Dist: matplotlib ; extra == 'full'
Requires-Dist: networkx ; extra == 'full'
Requires-Dist: pandas ; extra == 'full'
Requires-Dist: tabulate ; extra == 'full'
Provides-Extra: graph
Requires-Dist: matplotlib ; extra == 'graph'
Requires-Dist: networkx ; extra == 'graph'
Provides-Extra: table
Requires-Dist: pandas ; extra == 'table'
Requires-Dist: tabulate ; extra == 'table'
